{
  "Top": "echo_effect",
  "RtlTop": "echo_effect",
  "RtlPrefix": "",
  "RtlSubPrefix": "echo_effect_",
  "SourceLanguage": "cpp",
  "HostMachineBits": "64",
  "FunctionProtocol": "ap_ctrl_hs",
  "ResetStyle": "control",
  "Target": {
    "Family": "zynq",
    "Device": "xc7z020",
    "Package": "-clg400",
    "Speed": "-1",
    "Triple": "fpga64-xilinx-none"
  },
  "Args": {
    "sample_in": {
      "index": "0",
      "direction": "in",
      "srcType": "float",
      "srcSize": "32",
      "hwRefs": [{
          "type": "register",
          "interface": "s_axi_control",
          "name": "sample_in",
          "usage": "data",
          "direction": "in"
        }]
    },
    "sample_out": {
      "index": "1",
      "direction": "out",
      "srcType": "float*",
      "srcSize": "32",
      "hwRefs": [
        {
          "type": "register",
          "interface": "s_axi_control",
          "name": "sample_out",
          "usage": "data",
          "direction": "out"
        },
        {
          "type": "register",
          "interface": "s_axi_control",
          "name": "sample_out_ctrl",
          "usage": "control",
          "direction": "out"
        }
      ]
    },
    "delay_ms": {
      "index": "2",
      "direction": "in",
      "srcType": "float",
      "srcSize": "32",
      "hwRefs": [{
          "type": "register",
          "interface": "s_axi_control",
          "name": "delay_ms",
          "usage": "data",
          "direction": "in"
        }]
    },
    "feedback_gain": {
      "index": "3",
      "direction": "in",
      "srcType": "float",
      "srcSize": "32",
      "hwRefs": [{
          "type": "register",
          "interface": "s_axi_control",
          "name": "feedback_gain",
          "usage": "data",
          "direction": "in"
        }]
    },
    "sample_rate": {
      "index": "4",
      "direction": "in",
      "srcType": "int",
      "srcSize": "32",
      "hwRefs": [{
          "type": "register",
          "interface": "s_axi_control",
          "name": "sample_rate",
          "usage": "data",
          "direction": "in"
        }]
    },
    "buffer": {
      "index": "5",
      "direction": "inout",
      "srcType": "*",
      "srcSize": "32",
      "hwRefs": [
        {
          "type": "interface",
          "interface": "m_axi_BUFFER_r",
          "name": "",
          "usage": "data",
          "direction": "inout"
        },
        {
          "type": "interface",
          "interface": "s_axi_control",
          "name": "",
          "usage": "address",
          "direction": "inout"
        }
      ]
    },
    "index": {
      "index": "6",
      "direction": "inout",
      "srcType": "int*",
      "srcSize": "32",
      "hwRefs": [
        {
          "type": "register",
          "interface": "s_axi_CTRL",
          "name": "index_i",
          "usage": "data",
          "direction": "in"
        },
        {
          "type": "register",
          "interface": "s_axi_CTRL",
          "name": "index_o",
          "usage": "data",
          "direction": "out"
        },
        {
          "type": "register",
          "interface": "s_axi_CTRL",
          "name": "index_o_ctrl",
          "usage": "control",
          "direction": "out"
        }
      ]
    }
  },
  "HlsSolution": {
    "FlowTarget": "vivado",
    "ConfigTcl": [
      "config_csim -code_analyzer=1",
      "config_export -format=ip_catalog",
      "config_export -flow=none"
    ],
    "ProfileOption": "0",
    "ProfileType": "none",
    "KernelName": "echo_effect"
  },
  "ClockInfo": {
    "ClockName": "ap_clk",
    "ClockPeriod": "20",
    "Uncertainty": "2",
    "IsCombinational": "0",
    "II": "62",
    "Latency": "61"
  },
  "Xdc": {"OocClocks": ["create_clock -name ap_clk -period 20.000 [get_ports ap_clk]"]},
  "Ipx": {
    "Vendor": "xilinx.com",
    "Library": "hls",
    "Name": "echo_effect",
    "Version": "1.0",
    "DisplayName": "Echo_effect",
    "Revision": "2114093282",
    "Description": "An IP generated by Vitis HLS",
    "Taxonomy": "\/VITIS_HLS_IP",
    "AutoFamilySupport": "",
    "ZipFile": "xilinx_com_hls_echo_effect_1_0.zip"
  },
  "Files": {
    "CSource": ["..\/..\/echo.cpp"],
    "Vhdl": [
      "impl\/vhdl\/echo_effect_BUFFER_r_m_axi.vhd",
      "impl\/vhdl\/echo_effect_control_s_axi.vhd",
      "impl\/vhdl\/echo_effect_CTRL_s_axi.vhd",
      "impl\/vhdl\/echo_effect_fadd_32ns_32ns_32_4_full_dsp_1.vhd",
      "impl\/vhdl\/echo_effect_fmul_32ns_32ns_32_2_max_dsp_1.vhd",
      "impl\/vhdl\/echo_effect_sitofp_32ns_32_2_no_dsp_1.vhd",
      "impl\/vhdl\/echo_effect_srem_32ns_17ns_17_36_seq_1.vhd",
      "impl\/vhdl\/echo_effect_srem_32ns_17ns_32_36_seq_1.vhd",
      "impl\/vhdl\/echo_effect.vhd"
    ],
    "Verilog": [
      "impl\/verilog\/echo_effect_BUFFER_r_m_axi.v",
      "impl\/verilog\/echo_effect_control_s_axi.v",
      "impl\/verilog\/echo_effect_CTRL_s_axi.v",
      "impl\/verilog\/echo_effect_fadd_32ns_32ns_32_4_full_dsp_1.v",
      "impl\/verilog\/echo_effect_fmul_32ns_32ns_32_2_max_dsp_1.v",
      "impl\/verilog\/echo_effect_sitofp_32ns_32_2_no_dsp_1.v",
      "impl\/verilog\/echo_effect_srem_32ns_17ns_17_36_seq_1.v",
      "impl\/verilog\/echo_effect_srem_32ns_17ns_32_36_seq_1.v",
      "impl\/verilog\/echo_effect.v"
    ],
    "SwDriver": [
      "impl\/misc\/drivers\/echo_effect_v1_0\/data\/echo_effect.mdd",
      "impl\/misc\/drivers\/echo_effect_v1_0\/data\/echo_effect.tcl",
      "impl\/misc\/drivers\/echo_effect_v1_0\/data\/echo_effect.yaml",
      "impl\/misc\/drivers\/echo_effect_v1_0\/src\/CMakeLists.txt",
      "impl\/misc\/drivers\/echo_effect_v1_0\/src\/Makefile",
      "impl\/misc\/drivers\/echo_effect_v1_0\/src\/xecho_effect.c",
      "impl\/misc\/drivers\/echo_effect_v1_0\/src\/xecho_effect.h",
      "impl\/misc\/drivers\/echo_effect_v1_0\/src\/xecho_effect_hw.h",
      "impl\/misc\/drivers\/echo_effect_v1_0\/src\/xecho_effect_linux.c",
      "impl\/misc\/drivers\/echo_effect_v1_0\/src\/xecho_effect_sinit.c"
    ],
    "IpMisc": ["impl\/misc\/logo.png"],
    "Subcore": [
      "impl\/misc\/echo_effect_fadd_32ns_32ns_32_4_full_dsp_1_ip.tcl",
      "impl\/misc\/echo_effect_fmul_32ns_32ns_32_2_max_dsp_1_ip.tcl",
      "impl\/misc\/echo_effect_sitofp_32ns_32_2_no_dsp_1_ip.tcl"
    ],
    "CsynthXml": "syn\/report\/csynth.xml",
    "DebugDir": ".debug",
    "KernelXml": ".autopilot\/db\/kernel.internal.xml",
    "Xo": "",
    "XoHlsDir": "",
    "ProtoInst": [".debug\/echo_effect.protoinst"]
  },
  "SubcoreInfo": {
    "HasXpmMemory": false,
    "HasClockedDsp": false,
    "Ip": [
      {
        "Name": "echo_effect_fadd_32ns_32ns_32_4_full_dsp_1_ip",
        "Vlnv": "xilinx.com:ip:floating_point:7.1",
        "Params": "CONFIG.a_precision_type Single CONFIG.a_tuser_width 1 CONFIG.add_sub_value Add CONFIG.b_tuser_width 1 CONFIG.c_a_exponent_width 8 CONFIG.c_a_fraction_width 24 CONFIG.c_compare_operation Programmable CONFIG.c_has_divide_by_zero false CONFIG.c_has_invalid_op false CONFIG.c_has_overflow false CONFIG.c_has_underflow false CONFIG.c_latency 2 CONFIG.c_mult_usage Full_Usage CONFIG.c_optimization Speed_Optimized CONFIG.c_rate 1 CONFIG.c_result_exponent_width 8 CONFIG.c_result_fraction_width 24 CONFIG.component_name echo_effect_fadd_32ns_32ns_32_4_full_dsp_1_ip CONFIG.flow_control NonBlocking CONFIG.has_a_tlast false CONFIG.has_a_tuser false CONFIG.has_aclken true CONFIG.has_aresetn false CONFIG.has_b_tlast false CONFIG.has_b_tuser false CONFIG.has_operation_tlast false CONFIG.has_operation_tuser false CONFIG.has_result_tready false CONFIG.maximum_latency false CONFIG.operation_tuser_width 1 CONFIG.operation_type Add_Subtract CONFIG.result_precision_type Single CONFIG.result_tlast_behv Null"
      },
      {
        "Name": "echo_effect_fmul_32ns_32ns_32_2_max_dsp_1_ip",
        "Vlnv": "xilinx.com:ip:floating_point:7.1",
        "Params": "CONFIG.a_precision_type Single CONFIG.a_tuser_width 1 CONFIG.add_sub_value Both CONFIG.b_tuser_width 1 CONFIG.c_a_exponent_width 8 CONFIG.c_a_fraction_width 24 CONFIG.c_compare_operation Programmable CONFIG.c_has_divide_by_zero false CONFIG.c_has_invalid_op false CONFIG.c_has_overflow false CONFIG.c_has_underflow false CONFIG.c_latency 0 CONFIG.c_mult_usage Max_Usage CONFIG.c_optimization Speed_Optimized CONFIG.c_rate 1 CONFIG.c_result_exponent_width 8 CONFIG.c_result_fraction_width 24 CONFIG.component_name echo_effect_fmul_32ns_32ns_32_2_max_dsp_1_ip CONFIG.flow_control NonBlocking CONFIG.has_a_tlast false CONFIG.has_a_tuser false CONFIG.has_aclken false CONFIG.has_aresetn false CONFIG.has_b_tlast false CONFIG.has_b_tuser false CONFIG.has_operation_tlast false CONFIG.has_operation_tuser false CONFIG.has_result_tready false CONFIG.maximum_latency false CONFIG.operation_tuser_width 1 CONFIG.operation_type Multiply CONFIG.result_precision_type Single CONFIG.result_tlast_behv Null"
      },
      {
        "Name": "echo_effect_sitofp_32ns_32_2_no_dsp_1_ip",
        "Vlnv": "xilinx.com:ip:floating_point:7.1",
        "Params": "CONFIG.a_precision_type Custom CONFIG.a_tuser_width 1 CONFIG.add_sub_value Both CONFIG.b_tuser_width 1 CONFIG.c_a_exponent_width 32 CONFIG.c_a_fraction_width 0 CONFIG.c_compare_operation Programmable CONFIG.c_has_divide_by_zero false CONFIG.c_has_invalid_op false CONFIG.c_has_overflow false CONFIG.c_has_underflow false CONFIG.c_latency 0 CONFIG.c_mult_usage No_Usage CONFIG.c_optimization Speed_Optimized CONFIG.c_rate 1 CONFIG.c_result_exponent_width 8 CONFIG.c_result_fraction_width 24 CONFIG.component_name echo_effect_sitofp_32ns_32_2_no_dsp_1_ip CONFIG.flow_control NonBlocking CONFIG.has_a_tlast false CONFIG.has_a_tuser false CONFIG.has_aclken false CONFIG.has_aresetn false CONFIG.has_b_tlast false CONFIG.has_b_tuser false CONFIG.has_operation_tlast false CONFIG.has_operation_tuser false CONFIG.has_result_tready false CONFIG.maximum_latency false CONFIG.operation_tuser_width 1 CONFIG.operation_type Fixed_to_Float CONFIG.result_precision_type Single CONFIG.result_tlast_behv Null"
      }
    ]
  },
  "Interfaces": {
    "s_axi_CTRL": {
      "type": "axi4lite",
      "busTypeName": "aximm",
      "mode": "slave",
      "dataWidth": "32",
      "addrWidth": "5",
      "portPrefix": "s_axi_CTRL_",
      "paramPrefix": "C_S_AXI_CTRL_",
      "ports": [
        "s_axi_CTRL_ARADDR",
        "s_axi_CTRL_ARREADY",
        "s_axi_CTRL_ARVALID",
        "s_axi_CTRL_AWADDR",
        "s_axi_CTRL_AWREADY",
        "s_axi_CTRL_AWVALID",
        "s_axi_CTRL_BREADY",
        "s_axi_CTRL_BRESP",
        "s_axi_CTRL_BVALID",
        "s_axi_CTRL_RDATA",
        "s_axi_CTRL_RREADY",
        "s_axi_CTRL_RRESP",
        "s_axi_CTRL_RVALID",
        "s_axi_CTRL_WDATA",
        "s_axi_CTRL_WREADY",
        "s_axi_CTRL_WSTRB",
        "s_axi_CTRL_WVALID"
      ],
      "registers": [
        {
          "offset": "0x10",
          "name": "index_i",
          "access": "W",
          "description": "Data signal of index_i",
          "range": "32",
          "fields": [{
              "offset": "0",
              "width": "32",
              "name": "index_i",
              "access": "W",
              "description": "Bit 31 to 0 of index_i"
            }]
        },
        {
          "offset": "0x18",
          "name": "index_o",
          "access": "R",
          "description": "Data signal of index_o",
          "range": "32",
          "fields": [{
              "offset": "0",
              "width": "32",
              "name": "index_o",
              "access": "R",
              "description": "Bit 31 to 0 of index_o"
            }]
        },
        {
          "offset": "0x1c",
          "name": "index_o_ctrl",
          "access": "R",
          "description": "Control signal of index_o",
          "range": "32",
          "fields": [
            {
              "offset": "0",
              "width": "1",
              "name": "index_o_ap_vld",
              "access": "R",
              "description": "Control signal index_o_ap_vld"
            },
            {
              "offset": "1",
              "width": "31",
              "name": "RESERVED",
              "access": "R",
              "description": "Reserved.  0s on read."
            }
          ]
        }
      ],
      "constraints": [{
          "constraint_type": "pragma interface",
          "mode": "s_axilite",
          "register_option": "0",
          "offset": "16",
          "argName": "index"
        }]
    },
    "s_axi_control": {
      "type": "axi4lite",
      "busTypeName": "aximm",
      "mode": "slave",
      "dataWidth": "32",
      "addrWidth": "7",
      "portPrefix": "s_axi_control_",
      "paramPrefix": "C_S_AXI_CONTROL_",
      "ports": [
        "s_axi_control_ARADDR",
        "s_axi_control_ARREADY",
        "s_axi_control_ARVALID",
        "s_axi_control_AWADDR",
        "s_axi_control_AWREADY",
        "s_axi_control_AWVALID",
        "s_axi_control_BREADY",
        "s_axi_control_BRESP",
        "s_axi_control_BVALID",
        "s_axi_control_RDATA",
        "s_axi_control_RREADY",
        "s_axi_control_RRESP",
        "s_axi_control_RVALID",
        "s_axi_control_WDATA",
        "s_axi_control_WREADY",
        "s_axi_control_WSTRB",
        "s_axi_control_WVALID"
      ],
      "registers": [
        {
          "offset": "0x00",
          "name": "CTRL",
          "access": "RW",
          "description": "Control signals",
          "range": "32",
          "fields": [
            {
              "offset": "0",
              "width": "1",
              "name": "AP_START",
              "access": "RW",
              "description": "Control signal Register for 'ap_start'."
            },
            {
              "offset": "1",
              "width": "1",
              "name": "AP_DONE",
              "access": "R",
              "description": "Control signal Register for 'ap_done'."
            },
            {
              "offset": "2",
              "width": "1",
              "name": "AP_IDLE",
              "access": "R",
              "description": "Control signal Register for 'ap_idle'."
            },
            {
              "offset": "3",
              "width": "1",
              "name": "AP_READY",
              "access": "R",
              "description": "Control signal Register for 'ap_ready'."
            },
            {
              "offset": "4",
              "width": "3",
              "name": "RESERVED_1",
              "access": "R",
              "description": "Reserved.  0s on read."
            },
            {
              "offset": "7",
              "width": "1",
              "name": "AUTO_RESTART",
              "access": "RW",
              "description": "Control signal Register for 'auto_restart'."
            },
            {
              "offset": "8",
              "width": "1",
              "name": "RESERVED_2",
              "access": "R",
              "description": "Reserved.  0s on read."
            },
            {
              "offset": "9",
              "width": "1",
              "name": "INTERRUPT",
              "access": "R",
              "description": "Control signal Register for 'interrupt'."
            },
            {
              "offset": "10",
              "width": "22",
              "name": "RESERVED_3",
              "access": "R",
              "description": "Reserved.  0s on read."
            }
          ]
        },
        {
          "offset": "0x04",
          "name": "GIER",
          "access": "RW",
          "description": "Global Interrupt Enable Register",
          "range": "32",
          "fields": [
            {
              "offset": "0",
              "width": "1",
              "name": "Enable",
              "access": "RW",
              "description": "Master enable for the device interrupt output to the system interrupt controller: 0 = Disabled, 1 = Enabled"
            },
            {
              "offset": "1",
              "width": "31",
              "name": "RESERVED",
              "access": "R",
              "description": "Reserved.  0s on read."
            }
          ]
        },
        {
          "offset": "0x08",
          "name": "IP_IER",
          "access": "RW",
          "description": "IP Interrupt Enable Register",
          "range": "32",
          "fields": [
            {
              "offset": "0",
              "width": "1",
              "name": "CHAN0_INT_EN",
              "access": "RW",
              "description": "Enable Channel 0 (ap_done) Interrupt.  0 = Disabled, 1 = Enabled."
            },
            {
              "offset": "1",
              "width": "1",
              "name": "CHAN1_INT_EN",
              "access": "RW",
              "description": "Enable Channel 1 (ap_ready) Interrupt.  0 = Disabled, 1 = Enabled."
            },
            {
              "offset": "2",
              "width": "30",
              "name": "RESERVED_0",
              "access": "R",
              "description": "Reserved.  0s on read."
            }
          ]
        },
        {
          "offset": "0x0c",
          "name": "IP_ISR",
          "access": "RW",
          "description": "IP Interrupt Status Register",
          "range": "32",
          "fields": [
            {
              "offset": "0",
              "width": "1",
              "name": "CHAN0_INT_ST",
              "access": "RTOW",
              "description": "Channel 0 (ap_done) Interrupt Status. 0 = No Channel 0 interrupt, 1 = Channel 0 interrupt."
            },
            {
              "offset": "1",
              "width": "1",
              "name": "CHAN1_INT_ST",
              "access": "RTOW",
              "description": "Channel 1 (ap_ready) Interrupt Status. 0 = No Channel 1 interrupt, 1 = Channel 1 interrupt."
            },
            {
              "offset": "2",
              "width": "30",
              "name": "RESERVED_0",
              "access": "R",
              "description": "Reserved.  0s on read."
            }
          ]
        },
        {
          "offset": "0x10",
          "name": "sample_in",
          "access": "W",
          "description": "Data signal of sample_in",
          "range": "32",
          "fields": [{
              "offset": "0",
              "width": "32",
              "name": "sample_in",
              "access": "W",
              "description": "Bit 31 to 0 of sample_in"
            }]
        },
        {
          "offset": "0x18",
          "name": "sample_out",
          "access": "R",
          "description": "Data signal of sample_out",
          "range": "32",
          "fields": [{
              "offset": "0",
              "width": "32",
              "name": "sample_out",
              "access": "R",
              "description": "Bit 31 to 0 of sample_out"
            }]
        },
        {
          "offset": "0x1c",
          "name": "sample_out_ctrl",
          "access": "R",
          "description": "Control signal of sample_out",
          "range": "32",
          "fields": [
            {
              "offset": "0",
              "width": "1",
              "name": "sample_out_ap_vld",
              "access": "R",
              "description": "Control signal sample_out_ap_vld"
            },
            {
              "offset": "1",
              "width": "31",
              "name": "RESERVED",
              "access": "R",
              "description": "Reserved.  0s on read."
            }
          ]
        },
        {
          "offset": "0x28",
          "name": "delay_ms",
          "access": "W",
          "description": "Data signal of delay_ms",
          "range": "32",
          "fields": [{
              "offset": "0",
              "width": "32",
              "name": "delay_ms",
              "access": "W",
              "description": "Bit 31 to 0 of delay_ms"
            }]
        },
        {
          "offset": "0x30",
          "name": "feedback_gain",
          "access": "W",
          "description": "Data signal of feedback_gain",
          "range": "32",
          "fields": [{
              "offset": "0",
              "width": "32",
              "name": "feedback_gain",
              "access": "W",
              "description": "Bit 31 to 0 of feedback_gain"
            }]
        },
        {
          "offset": "0x38",
          "name": "sample_rate",
          "access": "W",
          "description": "Data signal of sample_rate",
          "range": "32",
          "fields": [{
              "offset": "0",
              "width": "32",
              "name": "sample_rate",
              "access": "W",
              "description": "Bit 31 to 0 of sample_rate"
            }]
        },
        {
          "offset": "0x40",
          "name": "buffer_r_r_1",
          "access": "W",
          "description": "Data signal of buffer_r_r",
          "range": "32",
          "fields": [{
              "offset": "0",
              "width": "32",
              "name": "buffer_r_r",
              "access": "W",
              "description": "Bit 31 to 0 of buffer_r_r"
            }]
        },
        {
          "offset": "0x44",
          "name": "buffer_r_r_2",
          "access": "W",
          "description": "Data signal of buffer_r_r",
          "range": "32",
          "fields": [{
              "offset": "0",
              "width": "32",
              "name": "buffer_r_r",
              "access": "W",
              "description": "Bit 63 to 32 of buffer_r_r"
            }]
        }
      ],
      "constraints": [
        {
          "constraint_type": "pragma interface",
          "mode": "s_axilite",
          "register_option": "0",
          "offset": "16",
          "argName": "sample_in"
        },
        {
          "constraint_type": "pragma interface",
          "mode": "s_axilite",
          "register_option": "0",
          "offset": "24",
          "argName": "sample_out"
        },
        {
          "constraint_type": "pragma interface",
          "mode": "s_axilite",
          "register_option": "0",
          "offset": "40",
          "argName": "delay_ms"
        },
        {
          "constraint_type": "pragma interface",
          "mode": "s_axilite",
          "register_option": "0",
          "offset": "48",
          "argName": "feedback_gain"
        },
        {
          "constraint_type": "pragma interface",
          "mode": "s_axilite",
          "register_option": "0",
          "offset": "56",
          "argName": "sample_rate"
        },
        {
          "constraint_type": "pragma interface",
          "mode": "s_axilite",
          "register_option": "0",
          "offset": "64",
          "argName": "buffer"
        }
      ]
    },
    "ap_clk": {
      "type": "clock",
      "busTypeName": "clock",
      "mode": "slave",
      "busParams": {
        "ASSOCIATED_BUSIF": "s_axi_CTRL:s_axi_control:m_axi_BUFFER_r",
        "ASSOCIATED_RESET": "ap_rst_n"
      },
      "portMap": {"ap_clk": "CLK"},
      "ports": ["ap_clk"]
    },
    "ap_rst_n": {
      "type": "reset",
      "busTypeName": "reset",
      "mode": "slave",
      "busParams": {"POLARITY": "ACTIVE_LOW"},
      "portMap": {"ap_rst_n": "RST"},
      "ports": ["ap_rst_n"]
    },
    "interrupt": {
      "type": "interrupt",
      "busTypeName": "interrupt",
      "mode": "master",
      "dataWidth": "1",
      "busParams": {"SENSITIVITY": "LEVEL_HIGH"},
      "portMap": {"interrupt": "INTERRUPT"},
      "ports": ["interrupt"]
    },
    "m_axi_BUFFER_r": {
      "type": "axi4full",
      "busTypeName": "aximm",
      "mode": "master",
      "dataWidth": "32",
      "addrWidth": "64",
      "portPrefix": "m_axi_BUFFER_r_",
      "paramPrefix": "C_M_AXI_BUFFER_R_",
      "preferredUsageValue": "MEMORY",
      "busParams": {
        "NUM_READ_OUTSTANDING": "16",
        "NUM_WRITE_OUTSTANDING": "16",
        "MAX_READ_BURST_LENGTH": "16",
        "MAX_WRITE_BURST_LENGTH": "16",
        "MAX_BURST_LENGTH": "256",
        "PROTOCOL": "AXI4",
        "READ_WRITE_MODE": "READ_WRITE",
        "HAS_BURST": "0",
        "SUPPORTS_NARROW_BURST": "0"
      },
      "ports": [
        "m_axi_BUFFER_r_ARADDR",
        "m_axi_BUFFER_r_ARBURST",
        "m_axi_BUFFER_r_ARCACHE",
        "m_axi_BUFFER_r_ARID",
        "m_axi_BUFFER_r_ARLEN",
        "m_axi_BUFFER_r_ARLOCK",
        "m_axi_BUFFER_r_ARPROT",
        "m_axi_BUFFER_r_ARQOS",
        "m_axi_BUFFER_r_ARREADY",
        "m_axi_BUFFER_r_ARREGION",
        "m_axi_BUFFER_r_ARSIZE",
        "m_axi_BUFFER_r_ARUSER",
        "m_axi_BUFFER_r_ARVALID",
        "m_axi_BUFFER_r_AWADDR",
        "m_axi_BUFFER_r_AWBURST",
        "m_axi_BUFFER_r_AWCACHE",
        "m_axi_BUFFER_r_AWID",
        "m_axi_BUFFER_r_AWLEN",
        "m_axi_BUFFER_r_AWLOCK",
        "m_axi_BUFFER_r_AWPROT",
        "m_axi_BUFFER_r_AWQOS",
        "m_axi_BUFFER_r_AWREADY",
        "m_axi_BUFFER_r_AWREGION",
        "m_axi_BUFFER_r_AWSIZE",
        "m_axi_BUFFER_r_AWUSER",
        "m_axi_BUFFER_r_AWVALID",
        "m_axi_BUFFER_r_BID",
        "m_axi_BUFFER_r_BREADY",
        "m_axi_BUFFER_r_BRESP",
        "m_axi_BUFFER_r_BUSER",
        "m_axi_BUFFER_r_BVALID",
        "m_axi_BUFFER_r_RDATA",
        "m_axi_BUFFER_r_RID",
        "m_axi_BUFFER_r_RLAST",
        "m_axi_BUFFER_r_RREADY",
        "m_axi_BUFFER_r_RRESP",
        "m_axi_BUFFER_r_RUSER",
        "m_axi_BUFFER_r_RVALID",
        "m_axi_BUFFER_r_WDATA",
        "m_axi_BUFFER_r_WID",
        "m_axi_BUFFER_r_WLAST",
        "m_axi_BUFFER_r_WREADY",
        "m_axi_BUFFER_r_WSTRB",
        "m_axi_BUFFER_r_WUSER",
        "m_axi_BUFFER_r_WVALID"
      ],
      "constraints": [
        {
          "constraint_type": "pragma interface",
          "mode": "m_axi",
          "register_option": "0",
          "offset": "slave",
          "latency": "0",
          "num_read_outstanding": "16",
          "num_write_outstanding": "16",
          "max_read_burst_length": "16",
          "max_write_burst_length": "16",
          "max_widen_bitwidth": "0",
          "channel_id": "0",
          "argName": "buffer"
        },
        {
          "constraint_type": "bitwidth",
          "orig_bitwidth": "32",
          "final_bitwidth": "32",
          "argName": "buffer"
        }
      ]
    }
  },
  "RtlPorts": {
    "s_axi_CTRL_AWVALID": {
      "dir": "in",
      "width": "1"
    },
    "s_axi_CTRL_AWREADY": {
      "dir": "out",
      "width": "1"
    },
    "s_axi_CTRL_AWADDR": {
      "dir": "in",
      "width": "5"
    },
    "s_axi_CTRL_WVALID": {
      "dir": "in",
      "width": "1"
    },
    "s_axi_CTRL_WREADY": {
      "dir": "out",
      "width": "1"
    },
    "s_axi_CTRL_WDATA": {
      "dir": "in",
      "width": "32"
    },
    "s_axi_CTRL_WSTRB": {
      "dir": "in",
      "width": "4"
    },
    "s_axi_CTRL_ARVALID": {
      "dir": "in",
      "width": "1"
    },
    "s_axi_CTRL_ARREADY": {
      "dir": "out",
      "width": "1"
    },
    "s_axi_CTRL_ARADDR": {
      "dir": "in",
      "width": "5"
    },
    "s_axi_CTRL_RVALID": {
      "dir": "out",
      "width": "1"
    },
    "s_axi_CTRL_RREADY": {
      "dir": "in",
      "width": "1"
    },
    "s_axi_CTRL_RDATA": {
      "dir": "out",
      "width": "32"
    },
    "s_axi_CTRL_RRESP": {
      "dir": "out",
      "width": "2"
    },
    "s_axi_CTRL_BVALID": {
      "dir": "out",
      "width": "1"
    },
    "s_axi_CTRL_BREADY": {
      "dir": "in",
      "width": "1"
    },
    "s_axi_CTRL_BRESP": {
      "dir": "out",
      "width": "2"
    },
    "s_axi_control_AWVALID": {
      "dir": "in",
      "width": "1"
    },
    "s_axi_control_AWREADY": {
      "dir": "out",
      "width": "1"
    },
    "s_axi_control_AWADDR": {
      "dir": "in",
      "width": "7"
    },
    "s_axi_control_WVALID": {
      "dir": "in",
      "width": "1"
    },
    "s_axi_control_WREADY": {
      "dir": "out",
      "width": "1"
    },
    "s_axi_control_WDATA": {
      "dir": "in",
      "width": "32"
    },
    "s_axi_control_WSTRB": {
      "dir": "in",
      "width": "4"
    },
    "s_axi_control_ARVALID": {
      "dir": "in",
      "width": "1"
    },
    "s_axi_control_ARREADY": {
      "dir": "out",
      "width": "1"
    },
    "s_axi_control_ARADDR": {
      "dir": "in",
      "width": "7"
    },
    "s_axi_control_RVALID": {
      "dir": "out",
      "width": "1"
    },
    "s_axi_control_RREADY": {
      "dir": "in",
      "width": "1"
    },
    "s_axi_control_RDATA": {
      "dir": "out",
      "width": "32"
    },
    "s_axi_control_RRESP": {
      "dir": "out",
      "width": "2"
    },
    "s_axi_control_BVALID": {
      "dir": "out",
      "width": "1"
    },
    "s_axi_control_BREADY": {
      "dir": "in",
      "width": "1"
    },
    "s_axi_control_BRESP": {
      "dir": "out",
      "width": "2"
    },
    "ap_clk": {
      "dir": "in",
      "width": "1"
    },
    "ap_rst_n": {
      "dir": "in",
      "width": "1"
    },
    "interrupt": {
      "dir": "out",
      "width": "1"
    },
    "m_axi_BUFFER_r_AWVALID": {
      "dir": "out",
      "width": "1"
    },
    "m_axi_BUFFER_r_AWREADY": {
      "dir": "in",
      "width": "1"
    },
    "m_axi_BUFFER_r_AWADDR": {
      "dir": "out",
      "width": "64"
    },
    "m_axi_BUFFER_r_AWID": {
      "dir": "out",
      "width": "1",
      "isVector": "true"
    },
    "m_axi_BUFFER_r_AWLEN": {
      "dir": "out",
      "width": "8"
    },
    "m_axi_BUFFER_r_AWSIZE": {
      "dir": "out",
      "width": "3"
    },
    "m_axi_BUFFER_r_AWBURST": {
      "dir": "out",
      "width": "2"
    },
    "m_axi_BUFFER_r_AWLOCK": {
      "dir": "out",
      "width": "2"
    },
    "m_axi_BUFFER_r_AWCACHE": {
      "dir": "out",
      "width": "4"
    },
    "m_axi_BUFFER_r_AWPROT": {
      "dir": "out",
      "width": "3"
    },
    "m_axi_BUFFER_r_AWQOS": {
      "dir": "out",
      "width": "4"
    },
    "m_axi_BUFFER_r_AWREGION": {
      "dir": "out",
      "width": "4"
    },
    "m_axi_BUFFER_r_AWUSER": {
      "dir": "out",
      "width": "1",
      "isVector": "true"
    },
    "m_axi_BUFFER_r_WVALID": {
      "dir": "out",
      "width": "1"
    },
    "m_axi_BUFFER_r_WREADY": {
      "dir": "in",
      "width": "1"
    },
    "m_axi_BUFFER_r_WDATA": {
      "dir": "out",
      "width": "32"
    },
    "m_axi_BUFFER_r_WSTRB": {
      "dir": "out",
      "width": "4"
    },
    "m_axi_BUFFER_r_WLAST": {
      "dir": "out",
      "width": "1"
    },
    "m_axi_BUFFER_r_WID": {
      "dir": "out",
      "width": "1",
      "isVector": "true"
    },
    "m_axi_BUFFER_r_WUSER": {
      "dir": "out",
      "width": "1",
      "isVector": "true"
    },
    "m_axi_BUFFER_r_ARVALID": {
      "dir": "out",
      "width": "1"
    },
    "m_axi_BUFFER_r_ARREADY": {
      "dir": "in",
      "width": "1"
    },
    "m_axi_BUFFER_r_ARADDR": {
      "dir": "out",
      "width": "64"
    },
    "m_axi_BUFFER_r_ARID": {
      "dir": "out",
      "width": "1",
      "isVector": "true"
    },
    "m_axi_BUFFER_r_ARLEN": {
      "dir": "out",
      "width": "8"
    },
    "m_axi_BUFFER_r_ARSIZE": {
      "dir": "out",
      "width": "3"
    },
    "m_axi_BUFFER_r_ARBURST": {
      "dir": "out",
      "width": "2"
    },
    "m_axi_BUFFER_r_ARLOCK": {
      "dir": "out",
      "width": "2"
    },
    "m_axi_BUFFER_r_ARCACHE": {
      "dir": "out",
      "width": "4"
    },
    "m_axi_BUFFER_r_ARPROT": {
      "dir": "out",
      "width": "3"
    },
    "m_axi_BUFFER_r_ARQOS": {
      "dir": "out",
      "width": "4"
    },
    "m_axi_BUFFER_r_ARREGION": {
      "dir": "out",
      "width": "4"
    },
    "m_axi_BUFFER_r_ARUSER": {
      "dir": "out",
      "width": "1",
      "isVector": "true"
    },
    "m_axi_BUFFER_r_RVALID": {
      "dir": "in",
      "width": "1"
    },
    "m_axi_BUFFER_r_RREADY": {
      "dir": "out",
      "width": "1"
    },
    "m_axi_BUFFER_r_RDATA": {
      "dir": "in",
      "width": "32"
    },
    "m_axi_BUFFER_r_RLAST": {
      "dir": "in",
      "width": "1"
    },
    "m_axi_BUFFER_r_RID": {
      "dir": "in",
      "width": "1",
      "isVector": "true"
    },
    "m_axi_BUFFER_r_RUSER": {
      "dir": "in",
      "width": "1",
      "isVector": "true"
    },
    "m_axi_BUFFER_r_RRESP": {
      "dir": "in",
      "width": "2"
    },
    "m_axi_BUFFER_r_BVALID": {
      "dir": "in",
      "width": "1"
    },
    "m_axi_BUFFER_r_BREADY": {
      "dir": "out",
      "width": "1"
    },
    "m_axi_BUFFER_r_BRESP": {
      "dir": "in",
      "width": "2"
    },
    "m_axi_BUFFER_r_BID": {
      "dir": "in",
      "width": "1",
      "isVector": "true"
    },
    "m_axi_BUFFER_r_BUSER": {
      "dir": "in",
      "width": "1",
      "isVector": "true"
    }
  },
  "ModuleInfo": {
    "Hierarchy": {
      "ModuleName": "echo_effect",
      "BindInstances": "fmul_32ns_32ns_32_2_max_dsp_1_U2 sitofp_32ns_32_2_no_dsp_1_U3 fmul_32ns_32ns_32_2_max_dsp_1_U2 add_ln317_fu_262_p2 sub_ln18_fu_276_p2 select_ln18_fu_286_p3 lshr_ln18_fu_314_p2 shl_ln18_fu_320_p2 val_fu_346_p3 result_2_fu_353_p2 result_fu_359_p3 icmp_ln14_fu_366_p2 sub_ln16_fu_372_p2 select_ln16_fu_378_p3 grp_fu_391_p0 srem_32ns_17ns_17_36_seq_1_U4 add_ln17_fu_425_p2 fmul_32ns_32ns_32_2_max_dsp_1_U2 fadd_32ns_32ns_32_4_full_dsp_1_U1 add_ln21_fu_461_p2 grp_fu_402_p0 srem_32ns_17ns_32_36_seq_1_U5 CTRL_s_axi_U control_s_axi_U BUFFER_r_m_axi_U"
    },
    "Info": {"echo_effect": {
        "FunctionProtocol": "ap_ctrl_hs",
        "isTaskLevelControl": "0",
        "isPipelined": "0",
        "isCombinational": "0",
        "isOneStateSeq": "0"
      }},
    "Metrics": {"echo_effect": {
        "Latency": {
          "LatencyBest": "61",
          "LatencyAvg": "61",
          "LatencyWorst": "61",
          "PipelineII": "62",
          "PipelineDepth": "",
          "PipelineType": "no"
        },
        "Timing": {
          "Target": "20.00",
          "Uncertainty": "2.00",
          "Estimate": "18.000"
        },
        "Area": {
          "BRAM_18K": "4",
          "AVAIL_BRAM": "280",
          "UTIL_BRAM": "1",
          "DSP": "5",
          "AVAIL_DSP": "220",
          "UTIL_DSP": "2",
          "FF": "2945",
          "AVAIL_FF": "106400",
          "UTIL_FF": "2",
          "LUT": "3889",
          "AVAIL_LUT": "53200",
          "UTIL_LUT": "7",
          "URAM": "0",
          "AVAIL_URAM": "0",
          "UTIL_URAM": "0"
        }
      }}
  },
  "GenerateBdFiles": "0",
  "GenData": {
    "DataVersion": "0.2",
    "Time": "2025-05-21 19:02:18 +0200",
    "ToolName": "vitis_hls",
    "ToolVersion": "2024.1"
  }
}
